[
  {
    "timeStamps": {
      "createdAt": "2026-02-07T06:29:09.000Z",
      "endedAt": "2026-02-07T06:29:11.000Z",
      "executionDuration": null
    },
    "circuitBatchNumQubits": [],
    "circuitBatchDepth": [],
    "sites": [],
    "rabiArray": [],
    "detuningArray": [],
    "phaseArray": [],
    "filling": [],
    "queuePosition": null,
    "queueDepth": null,
    "measurements": [],
    "prelight": false,
    "_id": "6986dbab851593b7018ea40a",
    "email": "spwotton@gmail.com",
    "user": "69502742771cbcafd266663a",
    "qbraidDeviceId": "rigetti_ankaa_3",
    "vendorDeviceId": "arn:aws:braket:us-west-1::device/qpu/rigetti/Ankaa-3",
    "qbraidJobId": "rigetti_ankaa_3-spwotton-qjob-jjoa47u8eoclc22r06ab",
    "status": "COMPLETED",
    "qbraidStatus": "COMPLETED",
    "vendor": "aws",
    "provider": "rigetti",
    "escrow": 0,
    "shots": 2048,
    "openQasm": "OPENQASM 3.0;\ninclude \"stdgates.inc\";\n\n// E \u2014 Original GoldenGHZ (Ry=\u03c6\u03c0=291.25\u00b0) \u2014 GoldenGHZ Validation\n// Experiment: GOLDEN_GHZ_Tycho_Validation_2026_02_07\n// Angle: 5.0832036923 rad = 291.2461 deg\n\nqubit[4] q;\nbit[4] c;\n\n// State preparation: Ry(theta) on q[0]\nry(5.083203692315259) q[0];\n\n// CNOT entanglement chain: creates GHZ state\ncx q[0], q[1];\ncx q[1], q[2];\ncx q[2], q[3];\n\n// Full 4-qubit measurement\nc[0] = measure q[0];\nc[1] = measure q[1];\nc[2] = measure q[2];\nc[3] = measure q[3];\n",
    "experimentType": "gate_model",
    "logo": "https://qbraid-static.s3.amazonaws.com/lab-docs/logos-full/rigetti.png",
    "logoDark": "https://qbraid-static.s3.amazonaws.com/lab-docs/logos-full/rigetti_dark.png",
    "tags": [
      "GOLDEN_GHZ_Tycho_Validation_2026_02_07",
      "E_Original_PhiPi"
    ],
    "createdAt": "2026-02-07T06:29:00.008Z",
    "updatedAt": "2026-02-07T06:29:20.877Z",
    "vendorJobId": "arn:aws:braket:us-west-1:592242689881:quantum-task/cfae85bc-2a0f-4043-b2b4-5ce63afae420",
    "cost": 214.32,
    "measurementCounts": {
      "1000": 58,
      "1001": 4,
      "1010": 4,
      "1011": 20,
      "1100": 18,
      "1101": 19,
      "1110": 45,
      "1111": 548,
      "0000": 1236,
      "0011": 15,
      "0100": 8,
      "0001": 32,
      "0010": 15,
      "0111": 21,
      "0110": 3,
      "0101": 2
    }
  },
  {
    "timeStamps": {
      "createdAt": "2026-02-07T06:29:08.000Z",
      "endedAt": "2026-02-07T06:29:12.000Z",
      "executionDuration": null
    },
    "circuitBatchNumQubits": [],
    "circuitBatchDepth": [],
    "sites": [],
    "rabiArray": [],
    "detuningArray": [],
    "phaseArray": [],
    "filling": [],
    "queuePosition": null,
    "queueDepth": null,
    "measurements": [],
    "prelight": false,
    "_id": "6986dbaac1f4b91990d22c9b",
    "email": "spwotton@gmail.com",
    "user": "69502742771cbcafd266663a",
    "qbraidDeviceId": "rigetti_ankaa_3",
    "vendorDeviceId": "arn:aws:braket:us-west-1::device/qpu/rigetti/Ankaa-3",
    "qbraidJobId": "rigetti_ankaa_3-spwotton-qjob-vcwra666i5vzywmn78sj",
    "status": "COMPLETED",
    "qbraidStatus": "COMPLETED",
    "vendor": "aws",
    "provider": "rigetti",
    "escrow": 0,
    "shots": 2048,
    "openQasm": "OPENQASM 3.0;\ninclude \"stdgates.inc\";\n\n// D \u2014 Anti-Tycho (Ry=51.77\u00b0) \u2014 GoldenGHZ Validation\n// Experiment: GOLDEN_GHZ_Tycho_Validation_2026_02_07\n// Angle: 0.9035569538 rad = 51.7700 deg\n\nqubit[4] q;\nbit[4] c;\n\n// State preparation: Ry(theta) on q[0]\nry(0.903556953757464) q[0];\n\n// CNOT entanglement chain: creates GHZ state\ncx q[0], q[1];\ncx q[1], q[2];\ncx q[2], q[3];\n\n// Full 4-qubit measurement\nc[0] = measure q[0];\nc[1] = measure q[1];\nc[2] = measure q[2];\nc[3] = measure q[3];\n",
    "experimentType": "gate_model",
    "logo": "https://qbraid-static.s3.amazonaws.com/lab-docs/logos-full/rigetti.png",
    "logoDark": "https://qbraid-static.s3.amazonaws.com/lab-docs/logos-full/rigetti_dark.png",
    "tags": [
      "GOLDEN_GHZ_Tycho_Validation_2026_02_07",
      "D_Anti_Tycho"
    ],
    "createdAt": "2026-02-07T06:28:58.142Z",
    "updatedAt": "2026-02-07T06:29:22.017Z",
    "vendorJobId": "arn:aws:braket:us-west-1:592242689881:quantum-task/0743a719-ee94-4c42-a543-6a4288250fb3",
    "cost": 214.32,
    "measurementCounts": {
      "1000": 59,
      "1001": 7,
      "1010": 1,
      "1011": 14,
      "1100": 13,
      "1101": 11,
      "1110": 22,
      "1111": 308,
      "0000": 1519,
      "0010": 20,
      "0111": 23,
      "0011": 12,
      "0100": 6,
      "0001": 29,
      "0101": 3,
      "0110": 1
    }
  },
  {
    "timeStamps": {
      "createdAt": "2026-02-07T06:29:07.000Z",
      "endedAt": "2026-02-07T06:29:10.000Z",
      "executionDuration": null
    },
    "circuitBatchNumQubits": [],
    "circuitBatchDepth": [],
    "sites": [],
    "rabiArray": [],
    "detuningArray": [],
    "phaseArray": [],
    "filling": [],
    "queuePosition": null,
    "queueDepth": null,
    "measurements": [],
    "prelight": false,
    "_id": "6986dba8c1f4b997bdd22c86",
    "email": "spwotton@gmail.com",
    "user": "69502742771cbcafd266663a",
    "qbraidDeviceId": "rigetti_ankaa_3",
    "vendorDeviceId": "arn:aws:braket:us-west-1::device/qpu/rigetti/Ankaa-3",
    "qbraidJobId": "rigetti_ankaa_3-spwotton-qjob-6b7hs0n3t7s3qd8jt4j0",
    "status": "COMPLETED",
    "qbraidStatus": "COMPLETED",
    "vendor": "aws",
    "provider": "rigetti",
    "escrow": 0,
    "shots": 2048,
    "openQasm": "OPENQASM 3.0;\ninclude \"stdgates.inc\";\n\n// C \u2014 \u03c6-Optimal (Ry=101.72\u00b0) \u2014 GoldenGHZ Validation\n// Experiment: GOLDEN_GHZ_Tycho_Validation_2026_02_07\n// Angle: 1.7753489151 rad = 101.7200 deg\n\nqubit[4] q;\nbit[4] c;\n\n// State preparation: Ry(theta) on q[0]\nry(1.775348915128632) q[0];\n\n// CNOT entanglement chain: creates GHZ state\ncx q[0], q[1];\ncx q[1], q[2];\ncx q[2], q[3];\n\n// Full 4-qubit measurement\nc[0] = measure q[0];\nc[1] = measure q[1];\nc[2] = measure q[2];\nc[3] = measure q[3];\n",
    "experimentType": "gate_model",
    "logo": "https://qbraid-static.s3.amazonaws.com/lab-docs/logos-full/rigetti.png",
    "logoDark": "https://qbraid-static.s3.amazonaws.com/lab-docs/logos-full/rigetti_dark.png",
    "tags": [
      "GOLDEN_GHZ_Tycho_Validation_2026_02_07",
      "C_Phi_Optimal"
    ],
    "createdAt": "2026-02-07T06:28:56.310Z",
    "updatedAt": "2026-02-07T06:29:21.256Z",
    "vendorJobId": "arn:aws:braket:us-west-1:592242689881:quantum-task/f7dd2007-a48e-40ec-869c-c112a4c2c4fe",
    "cost": 214.32,
    "measurementCounts": {
      "1000": 50,
      "1001": 3,
      "1010": 4,
      "1011": 42,
      "1100": 40,
      "1101": 37,
      "1110": 80,
      "1111": 945,
      "0000": 736,
      "0111": 45,
      "0001": 22,
      "0011": 12,
      "0010": 9,
      "0110": 8,
      "0100": 14,
      "0101": 1
    }
  },
  {
    "timeStamps": {
      "createdAt": "2026-02-07T06:29:05.000Z",
      "endedAt": "2026-02-07T06:29:08.000Z",
      "executionDuration": null
    },
    "circuitBatchNumQubits": [],
    "circuitBatchDepth": [],
    "sites": [],
    "rabiArray": [],
    "detuningArray": [],
    "phaseArray": [],
    "filling": [],
    "queuePosition": null,
    "queueDepth": null,
    "measurements": [],
    "prelight": false,
    "_id": "6986dba685159347a28ea3f5",
    "email": "spwotton@gmail.com",
    "user": "69502742771cbcafd266663a",
    "qbraidDeviceId": "rigetti_ankaa_3",
    "vendorDeviceId": "arn:aws:braket:us-west-1::device/qpu/rigetti/Ankaa-3",
    "qbraidJobId": "rigetti_ankaa_3-spwotton-qjob-5yultc1etj9it59w9if4",
    "status": "COMPLETED",
    "qbraidStatus": "COMPLETED",
    "vendor": "aws",
    "provider": "rigetti",
    "escrow": 0,
    "shots": 2048,
    "openQasm": "OPENQASM 3.0;\ninclude \"stdgates.inc\";\n\n// B \u2014 Tycho Twist (Ry=128.23\u00b0) \u2014 GoldenGHZ Validation\n// Experiment: GOLDEN_GHZ_Tycho_Validation_2026_02_07\n// Angle: 2.2380356998 rad = 128.2300 deg\n\nqubit[4] q;\nbit[4] c;\n\n// State preparation: Ry(theta) on q[0]\nry(2.238035699832329) q[0];\n\n// CNOT entanglement chain: creates GHZ state\ncx q[0], q[1];\ncx q[1], q[2];\ncx q[2], q[3];\n\n// Full 4-qubit measurement\nc[0] = measure q[0];\nc[1] = measure q[1];\nc[2] = measure q[2];\nc[3] = measure q[3];\n",
    "experimentType": "gate_model",
    "logo": "https://qbraid-static.s3.amazonaws.com/lab-docs/logos-full/rigetti.png",
    "logoDark": "https://qbraid-static.s3.amazonaws.com/lab-docs/logos-full/rigetti_dark.png",
    "tags": [
      "GOLDEN_GHZ_Tycho_Validation_2026_02_07",
      "B_Tycho_Twist"
    ],
    "createdAt": "2026-02-07T06:28:54.326Z",
    "updatedAt": "2026-02-07T06:30:59.019Z",
    "vendorJobId": "arn:aws:braket:us-west-1:592242689881:quantum-task/6036df6b-afbd-4cd9-93da-f1ea219bca27",
    "cost": 214.32,
    "measurementCounts": {
      "1000": 49,
      "1001": 4,
      "1010": 5,
      "1011": 47,
      "1100": 40,
      "1101": 46,
      "1110": 92,
      "1111": 1275,
      "0111": 41,
      "0000": 407,
      "0110": 5,
      "0010": 9,
      "0100": 9,
      "0011": 6,
      "0101": 7,
      "0001": 6
    }
  },
  {
    "timeStamps": {
      "createdAt": "2026-02-07T06:29:04.000Z",
      "endedAt": "2026-02-07T06:29:09.000Z",
      "executionDuration": null
    },
    "circuitBatchNumQubits": [],
    "circuitBatchDepth": [],
    "sites": [],
    "rabiArray": [],
    "detuningArray": [],
    "phaseArray": [],
    "filling": [],
    "queuePosition": null,
    "queueDepth": null,
    "measurements": [],
    "prelight": false,
    "_id": "6986dba4fec94e0758fa3045",
    "email": "spwotton@gmail.com",
    "user": "69502742771cbcafd266663a",
    "qbraidDeviceId": "rigetti_ankaa_3",
    "vendorDeviceId": "arn:aws:braket:us-west-1::device/qpu/rigetti/Ankaa-3",
    "qbraidJobId": "rigetti_ankaa_3-spwotton-qjob-jpbqlc7j3pvbvy0ef6v1",
    "status": "COMPLETED",
    "qbraidStatus": "COMPLETED",
    "vendor": "aws",
    "provider": "rigetti",
    "escrow": 0,
    "shots": 2048,
    "openQasm": "OPENQASM 3.0;\ninclude \"stdgates.inc\";\n\n// A \u2014 Control GHZ (Ry=90\u00b0) \u2014 GoldenGHZ Validation\n// Experiment: GOLDEN_GHZ_Tycho_Validation_2026_02_07\n// Angle: 1.5707963268 rad = 90.0000 deg\n\nqubit[4] q;\nbit[4] c;\n\n// State preparation: Ry(theta) on q[0]\nry(1.570796326794897) q[0];\n\n// CNOT entanglement chain: creates GHZ state\ncx q[0], q[1];\ncx q[1], q[2];\ncx q[2], q[3];\n\n// Full 4-qubit measurement\nc[0] = measure q[0];\nc[1] = measure q[1];\nc[2] = measure q[2];\nc[3] = measure q[3];\n",
    "experimentType": "gate_model",
    "logo": "https://qbraid-static.s3.amazonaws.com/lab-docs/logos-full/rigetti.png",
    "logoDark": "https://qbraid-static.s3.amazonaws.com/lab-docs/logos-full/rigetti_dark.png",
    "tags": [
      "GOLDEN_GHZ_Tycho_Validation_2026_02_07",
      "A_Control_GHZ"
    ],
    "createdAt": "2026-02-07T06:28:52.415Z",
    "updatedAt": "2026-02-07T06:31:15.289Z",
    "vendorJobId": "arn:aws:braket:us-west-1:592242689881:quantum-task/fa367eba-152b-4dfe-9cb0-84b4af6cd413",
    "cost": 214.32,
    "measurementCounts": {
      "1000": 71,
      "1001": 6,
      "1010": 7,
      "1011": 29,
      "1100": 23,
      "1101": 35,
      "1110": 71,
      "1111": 771,
      "0100": 12,
      "0001": 19,
      "0000": 912,
      "0111": 55,
      "0010": 10,
      "0101": 6,
      "0011": 14,
      "0110": 7
    }
  }
]